uhttp_session.py
uhttp_session-0.2.0.dist-info/LICENSE
uhttp_session-0.2.0.dist-info/METADATA
uhttp_session-0.2.0.dist-info/WHEEL
uhttp_session-0.2.0.dist-info/RECORD
