Metadata-Version: 2.1
Name: uhttp-session
Version: 0.2.0
Summary: Session support for µHTTP
Home-page: https://github.com/0x67757300/uHTTP-Session
License: MIT
Author: gus
Author-email: 0x67757300@gmail.com
Requires-Python: >=3.9,<4.0
Classifier: License :: OSI Approved :: MIT License
Classifier: Programming Language :: Python :: 3
Classifier: Programming Language :: Python :: 3.9
Classifier: Programming Language :: Python :: 3.10
Classifier: Programming Language :: Python :: 3.11
Classifier: Programming Language :: Python :: 3.12
Requires-Dist: pyjwt (>=2.8.0,<3.0.0)
Requires-Dist: uhttp (>=1.3.0,<2.0.0)
Project-URL: Repository, https://github.com/0x67757300/uHTTP-Session
